pycw_fn-0.1.2.dist-info/METADATA
pycw_fn-0.1.2.dist-info/WHEEL
pycw_fn/__init__.py
pycw_fn/pycw_fn.pypy39-pp73-x86-linux-gnu.so
pycw_fn-0.1.2.dist-info/RECORD
