Metadata-Version: 2.1
Name: pycw_fn
Version: 0.1.2
Classifier: Programming Language :: Rust
Classifier: Programming Language :: Python :: Implementation :: CPython
Classifier: Programming Language :: Python :: Implementation :: PyPy
Requires-Dist: delegateto>=1.5
Requires-Dist: numpy>=1.25
Keywords: piecewise function,math,science
Requires-Python: >=3.7
Project-URL: Bug Tracker, https://github.com/SV-97/pycw_fn/issues
Project-URL: Homepage, https://github.com/SV-97/pycw_fn
